yangify/__init__.py
yangify/linter/__init__.py
yangify/model_filter/__init__.py
yangify/parser/__init__.py
yangify/parser/text_tree.py
yangify/translator/__init__.py
yangify/translator/config_tree.py
yangify-0.1.3.dist-info/LICENSE
yangify-0.1.3.dist-info/WHEEL
yangify-0.1.3.dist-info/METADATA
yangify-0.1.3.dist-info/RECORD
