Metadata-Version: 2.1
Name: yangify
Version: 0.1.3
Summary: Library to help parsing/translating YANG models from/to native text/structures
License: Apache-2.0
Author: David Barroso
Author-email: dbarrosop@dravetech.com
Requires-Python: >=3.6,<4.0
Classifier: License :: OSI Approved :: Apache Software License
Classifier: Programming Language :: Python :: 3
Classifier: Programming Language :: Python :: 3.6
Classifier: Programming Language :: Python :: 3.7
Classifier: Programming Language :: Python :: 3.8
Classifier: Programming Language :: Python :: 3.9
Requires-Dist: dataclasses (>=0.6.0,<0.7.0); python_version >= "3.6" and python_version < "3.7"
Requires-Dist: yangson (==1.3.45)
